{"cameraMode":{"drawMode":0,"name":"Shaded","section":"Shading Mode"},"sceneLighting":false,"audioPlay":false,"sceneViewState":{"m_AlwaysRefresh":false,"showFog":true,"showSkybox":false,"showFlares":true,"showImageEffects":true,"showParticleSystems":true,"showVisualEffectGraphs":true,"m_FxEnabled":true},"in2DMode":false,"pivot":{"x":-1.88461172580719,"y":0.08406092971563339,"z":-1.233384132385254},"rotation":{"x":-0.15208062529563905,"y":0.6021021008491516,"z":-0.11817646771669388,"w":-0.7748441100120544},"size":0.6171573400497437,"orthographic":false}